ursa_bbs_signatures/__init__.py
ursa_bbs_signatures/api.py
ursa_bbs_signatures/bbs.dll
ursa_bbs_signatures/version.py
ursa_bbs_signatures/_ffi/ExternError.py
ursa_bbs_signatures/_ffi/FfiException.py
ursa_bbs_signatures/_ffi/__init__.py
ursa_bbs_signatures/_ffi/ffi_util.py
ursa_bbs_signatures/_ffi/bindings/__init__.py
ursa_bbs_signatures/_ffi/bindings/bbs_blind_commitment.py
ursa_bbs_signatures/_ffi/bindings/bbs_blind_sign.py
ursa_bbs_signatures/_ffi/bindings/bbs_create_proof.py
ursa_bbs_signatures/_ffi/bindings/bbs_sign.py
ursa_bbs_signatures/_ffi/bindings/bbs_verify.py
ursa_bbs_signatures/_ffi/bindings/bbs_verify_blind_commitment.py
ursa_bbs_signatures/_ffi/bindings/bbs_verify_proof.py
ursa_bbs_signatures/_ffi/bindings/bls.py
ursa_bbs_signatures/models/BbsException.py
ursa_bbs_signatures/models/BlindSignRequest.py
ursa_bbs_signatures/models/BlindedCommitment.py
ursa_bbs_signatures/models/CreateBlindedCommitmentRequest.py
ursa_bbs_signatures/models/CreateProofRequest.py
ursa_bbs_signatures/models/IndexedMessage.py
ursa_bbs_signatures/models/ProofMessage.py
ursa_bbs_signatures/models/SignRequest.py
ursa_bbs_signatures/models/SignatureProofStatus.py
ursa_bbs_signatures/models/UnblindSignatureRequest.py
ursa_bbs_signatures/models/VerifyBlindedCommitmentRequest.py
ursa_bbs_signatures/models/VerifyProofRequest.py
ursa_bbs_signatures/models/VerifyRequest.py
ursa_bbs_signatures/models/__init__.py
ursa_bbs_signatures/models/keys/BbsKey.py
ursa_bbs_signatures/models/keys/BlindedBlsKeyPair.py
ursa_bbs_signatures/models/keys/BlsKeyPair.py
ursa_bbs_signatures/models/keys/__init__.py
ursa_bbs_signatures/models/keys/test/__init__.py
ursa_bbs_signatures/models/keys/test/test_BlindedBlsKeyPair.py
ursa_bbs_signatures/models/keys/test/test_BlsKeyPair.py
ursa_bbs_signatures/test/__init__.py
ursa_bbs_signatures/test/fixtures.py
ursa_bbs_signatures/test/test_api_blind_commitment.py
ursa_bbs_signatures/test/test_api_blind_sign.py
ursa_bbs_signatures/test/test_api_sign.py
ursa_bbs_signatures-1.0.1.dist-info/METADATA
ursa_bbs_signatures-1.0.1.dist-info/WHEEL
ursa_bbs_signatures-1.0.1.dist-info/top_level.txt
ursa_bbs_signatures-1.0.1.dist-info/RECORD
