Metadata-Version: 2.1
Name: ursa-bbs-signatures
Version: 1.0.1
Summary: UNKNOWN
Home-page: https://github.com/mattrglobal/ffi-bbs-signatures
Author: Hyperledger Aries Contributors
Author-email: aries@lists.hyperledger.org
License: UNKNOWN
Platform: UNKNOWN
Classifier: Programming Language :: Python :: 3
Classifier: License :: OSI Approved :: Apache Software License
Classifier: License :: OSI Approved :: MIT License
Classifier: Operating System :: OS Independent
Requires-Python: >=3.6.3
